{"brand":"Hodkiewicz and Sons","swell":1.0,"height":3.1,"width":0.6,"thickness":0.5,"userWeightMin":22,"userWeightMax":32}
{"brand":"Mosciski, Funk and Luettgen","swell":1.0,"height":2.4,"width":0.7,"thickness":0.5,"userWeightMin":73,"userWeightMax":83}
{"brand":"Corwin, Farrell and Koelpin","swell":1.7,"height":1.7,"width":0.7,"thickness":0.6,"userWeightMin":65,"userWeightMax":75}
{"brand":"Armstrong Inc","swell":0.8,"height":2.4,"width":0.6,"thickness":0.4,"userWeightMin":81,"userWeightMax":91}
{"brand":"Nolan Inc","swell":1.6,"height":2.0,"width":0.5,"thickness":0.6,"userWeightMin":80,"userWeightMax":90}
{"brand":"McLaughlin Group","swell":1.8,"height":1.8,"width":0.6,"thickness":0.8,"userWeightMin":10,"userWeightMax":20}
{"brand":"Bechtelar, Hand and Walker","swell":2.1,"height":2.2,"width":0.7,"thickness":0.6,"userWeightMin":69,"userWeightMax":79}
{"brand":"Hackett-Parisian","swell":1.8,"height":2.2,"width":0.5,"thickness":0.5,"userWeightMin":15,"userWeightMax":25}
{"brand":"Sauer, Kuhlman and Schaefer","swell":1.8,"height":1.5,"width":0.5,"thickness":0.8,"userWeightMin":63,"userWeightMax":73}
{"brand":"Lesch-Ankunding","swell":1.5,"height":1.6,"width":0.5,"thickness":0.5,"userWeightMin":75,"userWeightMax":85}
{"brand":"Pfannerstill-Green","swell":1.6,"height":2.5,"width":0.4,"thickness":0.9,"userWeightMin":17,"userWeightMax":27}
{"brand":"Sawayn, Price and Mills","swell":1.1,"height":3.0,"width":0.5,"thickness":0.5,"userWeightMin":65,"userWeightMax":75}
{"brand":"Schowalter Group","swell":2.4,"height":2.0,"width":0.4,"thickness":0.8,"userWeightMin":51,"userWeightMax":61}
{"brand":"Gleason, Braun and Jast","swell":1.9,"height":2.1,"width":0.6,"thickness":0.7,"userWeightMin":49,"userWeightMax":59}
{"brand":"Murazik-Grant","swell":0.7,"height":1.6,"width":0.7,"thickness":0.4,"userWeightMin":54,"userWeightMax":64}
{"brand":"Ruecker and Sons","swell":0.6,"height":2.1,"width":0.5,"thickness":0.4,"userWeightMin":76,"userWeightMax":86}
{"brand":"Stanton Inc","swell":0.6,"height":1.6,"width":0.7,"thickness":0.8,"userWeightMin":78,"userWeightMax":88}
{"brand":"Metz, Hauck and Schultz","swell":0.7,"height":2.1,"width":0.5,"thickness":0.8,"userWeightMin":18,"userWeightMax":28}
{"brand":"Sporer-Hagenes","swell":1.5,"height":1.9,"width":0.6,"thickness":0.8,"userWeightMin":29,"userWeightMax":39}
{"brand":"Hyatt LLC","swell":1.7,"height":2.8,"width":0.5,"thickness":0.9,"userWeightMin":74,"userWeightMax":84}
{"brand":"Kassulke Inc","swell":1.2,"height":2.4,"width":0.5,"thickness":0.5,"userWeightMin":7,"userWeightMax":17}
{"brand":"Stoltenberg and Sons","swell":0.8,"height":2.9,"width":0.5,"thickness":0.5,"userWeightMin":92,"userWeightMax":102}
{"brand":"Crooks Group","swell":1.1,"height":2.1,"width":0.5,"thickness":0.6,"userWeightMin":99,"userWeightMax":109}
{"brand":"Bergnaum, Schoen and Satterfield","swell":2.0,"height":2.9,"width":0.6,"thickness":0.4,"userWeightMin":75,"userWeightMax":85}
{"brand":"Schaefer, Hermiston and Powlowski","swell":0.7,"height":1.8,"width":0.7,"thickness":0.7,"userWeightMin":11,"userWeightMax":21}
{"brand":"Paucek Group","swell":0.9,"height":3.0,"width":0.6,"thickness":0.5,"userWeightMin":13,"userWeightMax":23}
{"brand":"Rolfson LLC","swell":1.7,"height":1.8,"width":0.7,"thickness":0.8,"userWeightMin":44,"userWeightMax":54}
{"brand":"Batz, Ratke and Purdy","swell":1.4,"height":2.1,"width":0.7,"thickness":0.4,"userWeightMin":30,"userWeightMax":40}
{"brand":"Parker-Rolfson","swell":1.2,"height":2.9,"width":0.5,"thickness":0.7,"userWeightMin":8,"userWeightMax":18}
{"brand":"Weissnat Inc","swell":2.2,"height":1.7,"width":0.5,"thickness":0.6,"userWeightMin":41,"userWeightMax":51}
{"brand":"Orn-Swift","swell":2.5,"height":3.0,"width":0.5,"thickness":0.4,"userWeightMin":100,"userWeightMax":110}
{"brand":"Harris and Sons","swell":1.7,"height":2.6,"width":0.6,"thickness":0.6,"userWeightMin":26,"userWeightMax":36}
{"brand":"Fahey Group","swell":1.3,"height":3.0,"width":0.7,"thickness":0.4,"userWeightMin":66,"userWeightMax":76}
{"brand":"Bogan Inc","swell":1.2,"height":2.1,"width":0.6,"thickness":0.7,"userWeightMin":46,"userWeightMax":56}
{"brand":"Kshlerin-Marquardt","swell":1.5,"height":2.4,"width":0.4,"thickness":0.8,"userWeightMin":99,"userWeightMax":109}
{"brand":"Breitenberg, White and Kling","swell":0.6,"height":2.2,"width":0.6,"thickness":0.8,"userWeightMin":45,"userWeightMax":55}
{"brand":"Strosin Group","swell":1.6,"height":2.8,"width":0.5,"thickness":0.7,"userWeightMin":64,"userWeightMax":74}
{"brand":"Reynolds, Abbott and Hintz","swell":1.7,"height":2.6,"width":0.4,"thickness":0.7,"userWeightMin":2,"userWeightMax":12}
{"brand":"Denesik, Batz and Sipes","swell":0.7,"height":2.3,"width":0.6,"thickness":0.9,"userWeightMin":20,"userWeightMax":30}
{"brand":"Mayer-Marks","swell":2.0,"height":1.6,"width":0.4,"thickness":0.9,"userWeightMin":17,"userWeightMax":27}
{"brand":"Stamm, Spinka and Kessler","swell":0.6,"height":1.9,"width":0.5,"thickness":0.7,"userWeightMin":78,"userWeightMax":88}
{"brand":"Dickinson Inc","swell":1.3,"height":2.3,"width":0.6,"thickness":0.8,"userWeightMin":89,"userWeightMax":99}
{"brand":"Von Inc","swell":1.7,"height":2.5,"width":0.4,"thickness":0.6,"userWeightMin":54,"userWeightMax":64}
{"brand":"Kertzmann, Volkman and Moore","swell":2.2,"height":1.7,"width":0.5,"thickness":0.5,"userWeightMin":84,"userWeightMax":94}
{"brand":"Bosco-Cormier","swell":1.9,"height":2.5,"width":0.6,"thickness":0.8,"userWeightMin":52,"userWeightMax":62}
{"brand":"Macejkovic-Konopelski","swell":1.0,"height":3.2,"width":0.6,"thickness":0.5,"userWeightMin":83,"userWeightMax":93}
{"brand":"Kub Inc","swell":1.4,"height":1.8,"width":0.5,"thickness":0.5,"userWeightMin":69,"userWeightMax":79}
{"brand":"Pollich-Armstrong","swell":1.9,"height":1.7,"width":0.5,"thickness":0.8,"userWeightMin":27,"userWeightMax":37}
{"brand":"Emmerich-Marquardt","swell":1.3,"height":1.6,"width":0.4,"thickness":0.7,"userWeightMin":85,"userWeightMax":95}
{"brand":"Stracke-Fritsch","swell":1.4,"height":2.4,"width":0.5,"thickness":0.7,"userWeightMin":15,"userWeightMax":25}
{"brand":"Bergnaum and Sons","swell":1.4,"height":2.5,"width":0.7,"thickness":0.5,"userWeightMin":79,"userWeightMax":89}
{"brand":"Moen and Sons","swell":2.3,"height":1.9,"width":0.5,"thickness":0.6,"userWeightMin":8,"userWeightMax":18}
{"brand":"Crist-Stamm","swell":0.6,"height":2.9,"width":0.5,"thickness":0.7,"userWeightMin":12,"userWeightMax":22}
{"brand":"Lueilwitz-Corkery","swell":1.2,"height":2.3,"width":0.5,"thickness":0.9,"userWeightMin":15,"userWeightMax":25}
{"brand":"Donnelly, Stoltenberg and Jenkins","swell":0.7,"height":2.3,"width":0.6,"thickness":0.8,"userWeightMin":81,"userWeightMax":91}
{"brand":"Mertz and Sons","swell":2.3,"height":1.8,"width":0.5,"thickness":0.4,"userWeightMin":24,"userWeightMax":34}
{"brand":"Kirlin-Jast","swell":0.5,"height":2.2,"width":0.6,"thickness":0.5,"userWeightMin":24,"userWeightMax":34}
{"brand":"Bernhard Inc","swell":1.4,"height":2.6,"width":0.6,"thickness":0.6,"userWeightMin":76,"userWeightMax":86}
{"brand":"Walsh-Towne","swell":2.2,"height":1.7,"width":0.7,"thickness":0.8,"userWeightMin":32,"userWeightMax":42}
{"brand":"Schamberger, Williamson and Gleason","swell":1.2,"height":2.0,"width":0.7,"thickness":0.6,"userWeightMin":46,"userWeightMax":56}
{"brand":"Rosenbaum, Baumbach and Cummings","swell":2.5,"height":2.4,"width":0.6,"thickness":0.4,"userWeightMin":55,"userWeightMax":65}
{"brand":"Parker LLC","swell":1.8,"height":2.0,"width":0.6,"thickness":0.7,"userWeightMin":3,"userWeightMax":13}
{"brand":"Block LLC","swell":2.3,"height":2.5,"width":0.4,"thickness":0.6,"userWeightMin":83,"userWeightMax":93}
{"brand":"Dicki, Jones and Treutel","swell":1.5,"height":2.0,"width":0.5,"thickness":0.8,"userWeightMin":16,"userWeightMax":26}
{"brand":"Bogisich Inc","swell":2.3,"height":2.6,"width":0.7,"thickness":0.9,"userWeightMin":11,"userWeightMax":21}
{"brand":"Hartmann, Shields and Hilll","swell":0.6,"height":2.3,"width":0.4,"thickness":0.7,"userWeightMin":87,"userWeightMax":97}
{"brand":"Haag, Lowe and McDermott","swell":0.9,"height":3.1,"width":0.6,"thickness":0.8,"userWeightMin":22,"userWeightMax":32}
{"brand":"Collins Inc","swell":1.1,"height":2.5,"width":0.7,"thickness":0.7,"userWeightMin":15,"userWeightMax":25}
{"brand":"Herzog-Waelchi","swell":0.7,"height":2.6,"width":0.6,"thickness":0.6,"userWeightMin":26,"userWeightMax":36}
{"brand":"Heathcote, O'Hara and Cummerata","swell":1.1,"height":2.3,"width":0.6,"thickness":0.7,"userWeightMin":95,"userWeightMax":105}
{"brand":"Herzog and Sons","swell":1.2,"height":2.7,"width":0.4,"thickness":0.8,"userWeightMin":62,"userWeightMax":72}
{"brand":"Stanton, Hahn and Bogan","swell":2.1,"height":2.5,"width":0.6,"thickness":0.5,"userWeightMin":34,"userWeightMax":44}
{"brand":"Wunsch, Rolfson and Hamill","swell":0.6,"height":2.2,"width":0.5,"thickness":0.4,"userWeightMin":91,"userWeightMax":101}
{"brand":"Skiles-Connelly","swell":0.5,"height":2.4,"width":0.5,"thickness":0.8,"userWeightMin":66,"userWeightMax":76}
{"brand":"Lang, Hyatt and Adams","swell":0.7,"height":2.2,"width":0.7,"thickness":0.7,"userWeightMin":41,"userWeightMax":51}
{"brand":"Berge-Conn","swell":0.9,"height":3.1,"width":0.6,"thickness":0.7,"userWeightMin":3,"userWeightMax":13}
{"brand":"Frami, Murphy and Bradtke","swell":1.7,"height":3.0,"width":0.6,"thickness":0.9,"userWeightMin":26,"userWeightMax":36}
{"brand":"Hilll LLC","swell":1.8,"height":1.8,"width":0.4,"thickness":0.9,"userWeightMin":85,"userWeightMax":95}
{"brand":"Tremblay Inc","swell":2.4,"height":1.8,"width":0.5,"thickness":0.6,"userWeightMin":10,"userWeightMax":20}
{"brand":"Bartoletti Inc","swell":1.3,"height":1.9,"width":0.4,"thickness":0.4,"userWeightMin":55,"userWeightMax":65}
{"brand":"Ziemann, Fahey and Erdman","swell":2.5,"height":2.9,"width":0.5,"thickness":0.9,"userWeightMin":24,"userWeightMax":34}
{"brand":"Braun and Sons","swell":2.4,"height":2.2,"width":0.6,"thickness":0.5,"userWeightMin":68,"userWeightMax":78}
{"brand":"Boehm Group","swell":1.1,"height":2.3,"width":0.6,"thickness":0.7,"userWeightMin":82,"userWeightMax":92}
{"brand":"Abernathy LLC","swell":2.3,"height":3.0,"width":0.6,"thickness":0.5,"userWeightMin":74,"userWeightMax":84}
{"brand":"Dare Group","swell":2.3,"height":2.4,"width":0.7,"thickness":0.6,"userWeightMin":29,"userWeightMax":39}
{"brand":"Stark and Sons","swell":2.2,"height":2.7,"width":0.6,"thickness":0.8,"userWeightMin":21,"userWeightMax":31}
{"brand":"Murphy, Swift and Bartoletti","swell":0.6,"height":2.2,"width":0.5,"thickness":0.4,"userWeightMin":67,"userWeightMax":77}
{"brand":"Bradtke, Feil and Armstrong","swell":1.5,"height":2.5,"width":0.6,"thickness":0.9,"userWeightMin":12,"userWeightMax":22}
{"brand":"Haley-Grady","swell":1.4,"height":3.0,"width":0.7,"thickness":0.4,"userWeightMin":38,"userWeightMax":48}
{"brand":"Rosenbaum-Breitenberg","swell":2.4,"height":1.6,"width":0.7,"thickness":0.5,"userWeightMin":24,"userWeightMax":34}
{"brand":"Jast Inc","swell":0.8,"height":2.1,"width":0.5,"thickness":0.6,"userWeightMin":74,"userWeightMax":84}
{"brand":"Nader-Weissnat","swell":1.3,"height":2.9,"width":0.6,"thickness":0.9,"userWeightMin":41,"userWeightMax":51}
{"brand":"Bernhard-Cartwright","swell":0.7,"height":2.4,"width":0.5,"thickness":0.6,"userWeightMin":91,"userWeightMax":101}
{"brand":"Rice Inc","swell":0.7,"height":2.5,"width":0.6,"thickness":0.7,"userWeightMin":38,"userWeightMax":48}
{"brand":"Bosco and Sons","swell":0.9,"height":2.6,"width":0.6,"thickness":0.5,"userWeightMin":81,"userWeightMax":91}
{"brand":"Kuhic, Ondricka and Wuckert","swell":0.6,"height":1.8,"width":0.5,"thickness":0.5,"userWeightMin":89,"userWeightMax":99}
{"brand":"Bode, Cruickshank and Corwin","swell":1.8,"height":1.7,"width":0.7,"thickness":0.5,"userWeightMin":95,"userWeightMax":105}
{"brand":"Sawayn-DuBuque","swell":1.7,"height":2.3,"width":0.6,"thickness":0.5,"userWeightMin":100,"userWeightMax":110}
{"brand":"Bosco, Thompson and Gulgowski","swell":1.8,"height":1.9,"width":0.5,"thickness":0.8,"userWeightMin":90,"userWeightMax":100}
{"brand":"Bashirian Inc","swell":0.8,"height":2.8,"width":0.6,"thickness":0.6,"userWeightMin":93,"userWeightMax":103}